structllm/__init__.py
structllm/client.py
structllm-0.1.0.dist-info/METADATA
structllm-0.1.0.dist-info/WHEEL
structllm-0.1.0.dist-info/licenses/LICENSE
structllm-0.1.0.dist-info/RECORD
