Metadata-Version: 2.4
Name: structllm
Version: 0.1.0
Summary: Universal Python library for Structured Outputs with any LLM provider
Project-URL: Homepage, https://github.com/piotrmaciejbednarski/structllm
Project-URL: Documentation, https://github.com/piotrmaciejbednarski/structllm#readme
Project-URL: Repository, https://github.com/piotrmaciejbednarski/structllm.git
Project-URL: Issues, https://github.com/piotrmaciejbednarski/structllm/issues
Author-email: Piotr Bednarski <piotr.maciej.bednarski@gmail.com>
License: MIT
License-File: LICENSE
Keywords: ai,anthropic,json-schema,litellm,llm,openai,pydantic,structured-outputs
Classifier: Development Status :: 4 - Beta
Classifier: Intended Audience :: Developers
Classifier: License :: OSI Approved :: MIT License
Classifier: Operating System :: OS Independent
Classifier: Programming Language :: Python :: 3
Classifier: Programming Language :: Python :: 3.8
Classifier: Programming Language :: Python :: 3.9
Classifier: Programming Language :: Python :: 3.10
Classifier: Programming Language :: Python :: 3.11
Classifier: Programming Language :: Python :: 3.12
Classifier: Topic :: Scientific/Engineering :: Artificial Intelligence
Classifier: Topic :: Software Development :: Libraries :: Python Modules
Classifier: Typing :: Typed
Requires-Python: >=3.8
Requires-Dist: litellm>=1.0.0
Requires-Dist: pydantic>=2.0.0
Provides-Extra: dev
Requires-Dist: pytest>=7.0.0; extra == 'dev'
Requires-Dist: ruff>=0.1.0; extra == 'dev'
